hylight/__init__.py
hylight/constants.py
hylight/guess_width.py
hylight/loader.py
hylight/mode.py
hylight/mono_mode.py
hylight/multi_modes.py
hylight/npz.py
hylight/struct.py
hylight/typing.py
hylight/utils.py
hylight/cli/__init__.py
hylight/cli/modes.py
hylight/cli/pos.py
hylight/cli/script_utils.py
hylight/crystal/__init__.py
hylight/crystal/common.py
hylight/crystal/loader.py
hylight/findiff/__init__.py
hylight/findiff/collect.py
hylight/findiff/gen.py
hylight/jmol/__init__.py
hylight/phonopy/__init__.py
hylight/phonopy/loader.py
hylight/vasp/__init__.py
hylight/vasp/common.py
hylight/vasp/loader.py
hylight/vasp/utils.py
hylight-1.0.0.dist-info/METADATA
hylight-1.0.0.dist-info/WHEEL
hylight-1.0.0.dist-info/entry_points.txt
hylight-1.0.0.dist-info/licenses/LICENSE
hylight-1.0.0.dist-info/RECORD
