Metadata-Version: 2.3
Name: hylight
Version: 1.0.0
Summary: Hylight is post-processing package for luminescence related ab initio computations.
Project-URL: repository, https://github.com/PyDEF/hylight
Project-URL: documentation, https://pydef.github.io/hylight
Author-email: Théo Cavignac <theo.cavignac+dev@gmail.com>, The PyDEF Team <camille.latouch@cnrs-imn.fr>
License-Expression: EUPL-1.2
License-File: LICENSE
Keywords: chemistry,computational chemistry
Classifier: License :: OSI Approved :: European Union Public Licence 1.2 (EUPL 1.2)
Classifier: Operating System :: OS Independent
Classifier: Programming Language :: Python :: 3
Requires-Dist: numpy>=1.16
Requires-Dist: scipy>=1.3
Provides-Extra: dev
Requires-Dist: furo; extra == 'dev'
Requires-Dist: myst-nb; extra == 'dev'
Requires-Dist: myst-parser; extra == 'dev'
Requires-Dist: sphinx; extra == 'dev'
Provides-Extra: hdf5
Requires-Dist: h5py>=3.7; extra == 'hdf5'
Provides-Extra: phonopy
Requires-Dist: pyyaml; extra == 'phonopy'
Provides-Extra: plotting
Requires-Dist: matplotlib>=3.0; extra == 'plotting'
